highlight_extractor/__init__.py
highlight_extractor/core.py
highlight_extractor-0.1.0.dist-info/LICENSE
highlight_extractor-0.1.0.dist-info/METADATA
highlight_extractor-0.1.0.dist-info/WHEEL
highlight_extractor-0.1.0.dist-info/top_level.txt
highlight_extractor-0.1.0.dist-info/RECORD
