Metadata-Version: 2.1
Name: highlight-extractor
Version: 0.1.0
Summary: Audio highlight extractor using chroma and energy analysis
Home-page: https://github.com/marohan/highlight_extractor
Author: Marohan Min
Author-email: fragantmaro@naver.com
Classifier: Programming Language :: Python :: 3
Classifier: License :: OSI Approved :: MIT License
Requires-Python: >=3.7
License-File: LICENSE
Requires-Dist: librosa
Requires-Dist: numpy
Requires-Dist: scipy
Requires-Dist: pydub
